ScenarioReducer/.DS_Store
ScenarioReducer/__init__.py
ScenarioReducer/fast_forward.py
ScenarioReducer/scenario_reducer.py
scenarioreducer-1.0.0.dist-info/WHEEL
scenarioreducer-1.0.0.dist-info/METADATA
scenarioreducer-1.0.0.dist-info/RECORD
