Metadata-Version: 2.1
Name: ScenarioReducer
Version: 1.0.0
Summary: Scenario Reduction Algorithms in Stochastic Programming
Keywords: stochastic-programming,probability-metric,scenario-reduction,scenario-tree
Author-email: Daniele Giovani Gioia <daniele.gioia@polito.it>
Requires-Python: >=3.6
Classifier: License :: OSI Approved :: MIT License
Classifier: Intended Audience :: Science/Research
Classifier: Intended Audience :: Education
Classifier: Topic :: Scientific/Engineering :: Mathematics
Classifier: Programming Language :: Python
Classifier: Programming Language :: Python :: 3.6
Classifier: Programming Language :: Python :: 3.7
Classifier: Programming Language :: Python :: 3.8
Classifier: Programming Language :: Python :: 3.9
Classifier: Programming Language :: Python :: 3.10
Classifier: Programming Language :: Python :: 3.11
Classifier: Programming Language :: Python :: 3 :: Only
Requires-Dist: scipy
Requires-Dist: numpy
Requires-Dist: statsmodels
Requires-Dist: numba
Requires-Dist: pytest
Project-URL: changelog, https://github.com/DanieleGioia/ScenarioReducer/blob/main/CHANGELOG.md
Project-URL: repository, https://github.com/DanieleGioia/ScenarioReducer/blob/main/README.md
